README.md
hydra_plugins/__init__.py
hydra_plugins/mephisto_path_plugin.py
mephisto/README.md
mephisto/VERSION
mephisto/__init__.py
mephisto/abstractions/README.md
mephisto/abstractions/__init__.py
mephisto/abstractions/_subcomponents/README.md
mephisto/abstractions/_subcomponents/__init__.py
mephisto/abstractions/_subcomponents/agent_state.py
mephisto/abstractions/_subcomponents/channel.py
mephisto/abstractions/_subcomponents/task_builder.py
mephisto/abstractions/_subcomponents/task_runner.py
mephisto/abstractions/architect.py
mephisto/abstractions/architects/README.md
mephisto/abstractions/architects/__init__.py
mephisto/abstractions/architects/channels/__init__.py
mephisto/abstractions/architects/channels/websocket_channel.py
mephisto/abstractions/architects/ec2/.gitignore
mephisto/abstractions/architects/ec2/__init__.py
mephisto/abstractions/architects/ec2/cleanup_ec2_resources.py
mephisto/abstractions/architects/ec2/cleanup_ec2_server_by_name.py
mephisto/abstractions/architects/ec2/ec2_architect.py
mephisto/abstractions/architects/ec2/ec2_helpers.py
mephisto/abstractions/architects/ec2/fallback_server/README.md
mephisto/abstractions/architects/ec2/fallback_server/access_logs/README.md
mephisto/abstractions/architects/ec2/fallback_server/app.py
mephisto/abstractions/architects/ec2/fallback_server/fallback.service
mephisto/abstractions/architects/ec2/fallback_server/scripts/first_setup.sh
mephisto/abstractions/architects/ec2/fallback_server/scripts/run_server.sh
mephisto/abstractions/architects/ec2/fallback_server/templates/landing.html
mephisto/abstractions/architects/ec2/keypairs/README.md
mephisto/abstractions/architects/ec2/prepare_ec2_servers.py
mephisto/abstractions/architects/ec2/run_scripts/flask/init_server.sh
mephisto/abstractions/architects/ec2/run_scripts/flask/router.service
mephisto/abstractions/architects/ec2/run_scripts/flask/run_server.sh
mephisto/abstractions/architects/ec2/run_scripts/node/init_server.sh
mephisto-1.1.1.dist-info/entry_points.txt
mephisto-1.1.1.dist-info/LICENSE
mephisto-1.1.1.dist-info/WHEEL
mephisto-1.1.1.dist-info/METADATA
mephisto-1.1.1.dist-info/RECORD
